llmworkbook/__init__.py
llmworkbook/cli/__init__.py
llmworkbook/cli/cli.py
llmworkbook/config.py
llmworkbook/integrator.py
llmworkbook/providers.py
llmworkbook/runner.py
llmworkbook/tests/__init__.py
llmworkbook/tests/test_cli.py
llmworkbook/tests/test_config.py
llmworkbook/tests/test_integrator.py
llmworkbook/tests/test_providers.py
llmworkbook/tests/test_runner.py
llmworkbook/tests/test_utils.py
llmworkbook/tests/test_wrappers.py
llmworkbook/utilities.py
llmworkbook/utils.py
llmworkbook/wrappers.py
llmworkbook-1.4.5.dist-info/LICENSE
llmworkbook-1.4.5.dist-info/METADATA
llmworkbook-1.4.5.dist-info/WHEEL
llmworkbook-1.4.5.dist-info/entry_points.txt
llmworkbook-1.4.5.dist-info/RECORD
