Metadata-Version: 2.3
Name: llmworkbook
Version: 1.4.5
Summary: Effortlessly harness the power of LLMs on Excel and DataFrames—seamless, smart, and efficient!
License: MIT
Keywords: LLM,DataFrame,Excel Workbook,Excel,CSV,OpenAI,Ollama,Gpt4all,Python,async
Author: dhruv
Author-email: dhruv166arya@gmail.com
Requires-Python: >=3.11,<4.0
Classifier: Intended Audience :: Developers
Classifier: License :: Freeware
Classifier: License :: OSI Approved :: MIT License
Classifier: Natural Language :: English
Classifier: Programming Language :: Python :: 3
Classifier: Programming Language :: Python :: 3.11
Classifier: Programming Language :: Python :: 3.12
Classifier: Programming Language :: Python :: 3.13
Classifier: Topic :: Communications :: Chat
Classifier: Topic :: Scientific/Engineering :: Artificial Intelligence
Classifier: Topic :: Software Development :: Build Tools
Classifier: Topic :: Software Development :: Libraries :: Python Modules
Classifier: Topic :: Text Processing :: General
Classifier: Topic :: Utilities
Requires-Dist: aiohttp (>=3.12.15,<4.0.0)
Requires-Dist: anthropic (>=0.50.0,<0.51.0)
Requires-Dist: asyncio (>=3.4.3,<4.0.0)
Requires-Dist: nest-asyncio (>=1.6.0,<2.0.0)
Requires-Dist: openai (>=1.59.3,<2.0.0)
Requires-Dist: openpyxl (>=3.1.5,<4.0.0)
Requires-Dist: pandas (>=2.2.3,<3.0.0)
Requires-Dist: python-dotenv (>=1.0.1,<2.0.0)
Requires-Dist: requests (>=2.32.4,<3.0.0)
Requires-Dist: rich (>=13.9.4,<14.0.0)
Requires-Dist: urllib3 (>=2.5.0,<3.0.0)
Project-URL: Documentation, https://aryadhruv.github.io/LLMWorkbook/
Project-URL: Homepage, https://aryadhruv.github.io/LLMWorkbook/
Project-URL: Issues, https://github.com/aryadhruv/LLMWorkbook/issues
Project-URL: Repository, https://github.com/aryadhruv/LLMWorkbook
